helpers/__init__.py
helpers/helper_functions.py
compute_strings_data-0.1.4.dist-info/METADATA
compute_strings_data-0.1.4.dist-info/WHEEL
compute_strings_data-0.1.4.dist-info/top_level.txt
compute_strings_data-0.1.4.dist-info/RECORD
